{
  "designId": "design-1",
  "name": "Design 1 - Gradient Simple",
  "description": "Design avec fond dégradé coloré et mockup centré",
  "screens": [
    {
      "id": "screen-1",
      "label": "Écran 1",
      "editableZones": [
        {
          "id": "background",
          "type": "background",
          "selector": ".myScreen-design-1",
          "allowed": ["gradient", "color"],
          "current": "gradient"
        },
        {
          "id": "title",
          "type": "text",
          "selector": ".titleScreen-design-1",
          "allowed": ["edit"],
          "current": "Lorem ipsum sit amet consectetur"
        },
        {
          "id": "mockup",
          "type": "image",
          "selector": ".mockup-iphone-design-1",
          "allowed": ["replace"],
          "current": "/assets/mockup/adam-mockup-1.png"
        },
        {
          "id": "screenshot",
          "type": "image",
          "selector": ".visual-on-mockup",
          "allowed": ["upload", "replace"],
          "current": "/assets/tmp/screenshot.jpg"
        }
      ]
    },
    {
      "id": "screen-2",
      "label": "Écran 2",
      "editableZones": [
        {
          "id": "background",
          "type": "background",
          "selector": ".myScreen-design-1",
          "allowed": ["gradient", "color"],
          "current": "gradient"
        },
        {
          "id": "title",
          "type": "text",
          "selector": ".titleScreen-design-1",
          "allowed": ["edit"],
          "current": "Lorem ipsum sit amet consectetur"
        },
        {
          "id": "mockup",
          "type": "image",
          "selector": ".mockup-iphone-design-1",
          "allowed": ["replace"],
          "current": "/assets/mockup/adam-mockup-1.png"
        },
        {
          "id": "screenshot",
          "type": "image",
          "selector": ".visual-on-mockup",
          "allowed": ["upload", "replace"],
          "current": "/assets/tmp/screenshot.jpg"
        }
      ]
    },
    {
      "id": "screen-3",
      "label": "Écran 3",
      "editableZones": [
        {
          "id": "background",
          "type": "background",
          "selector": ".myScreen-design-1",
          "allowed": ["gradient", "color"],
          "current": "gradient"
        },
        {
          "id": "title",
          "type": "text",
          "selector": ".titleScreen-design-1",
          "allowed": ["edit"],
          "current": "Lorem ipsum sit amet consectetur"
        },
        {
          "id": "mockup",
          "type": "image",
          "selector": ".mockup-iphone-design-1",
          "allowed": ["replace"],
          "current": "/assets/mockup/adam-mockup-1.png"
        },
        {
          "id": "screenshot",
          "type": "image",
          "selector": ".visual-on-mockup",
          "allowed": ["upload", "replace"],
          "current": "/assets/tmp/screenshot.jpg"
        }
      ]
    },
    {
      "id": "screen-4",
      "label": "Écran 4",
      "editableZones": [
        {
          "id": "background",
          "type": "background",
          "selector": ".myScreen-design-1",
          "allowed": ["gradient", "color"],
          "current": "gradient"
        },
        {
          "id": "title",
          "type": "text",
          "selector": ".titleScreen-design-1",
          "allowed": ["edit"],
          "current": "Lorem ipsum sit amet consectetur"
        },
        {
          "id": "mockup",
          "type": "image",
          "selector": ".mockup-iphone-design-1",
          "allowed": ["replace"],
          "current": "/assets/mockup/adam-mockup-1.png"
        },
        {
          "id": "screenshot",
          "type": "image",
          "selector": ".visual-on-mockup",
          "allowed": ["upload", "replace"],
          "current": "/assets/tmp/screenshot.jpg"
        }
      ]
    },
    {
      "id": "screen-5",
      "label": "Écran 5",
      "editableZones": [
        {
          "id": "background",
          "type": "background",
          "selector": ".myScreen-design-1",
          "allowed": ["gradient", "color"],
          "current": "gradient"
        },
        {
          "id": "title",
          "type": "text",
          "selector": ".titleScreen-design-1",
          "allowed": ["edit"],
          "current": "Lorem ipsum sit amet consectetur"
        },
        {
          "id": "mockup",
          "type": "image",
          "selector": ".mockup-iphone-design-1",
          "allowed": ["replace"],
          "current": "/assets/mockup/adam-mockup-1.png"
        },
        {
          "id": "screenshot",
          "type": "image",
          "selector": ".visual-on-mockup",
          "allowed": ["upload", "replace"],
          "current": "/assets/tmp/screenshot.jpg"
        }
      ]
    }
  ]
}
